yls/__init__.py
yls/code_actions.py
yls/completer.py
yls/completion.py
yls/debugger.py
yls/hookspecs.py
yls/hover.py
yls/icons.py
yls/linting.py
yls/plugin_manager_provider.py
yls/py.typed
yls/server.py
yls/strings.py
yls/utils.py
yls/version.py
yls/yaramod_provider.py
yls-1.4.4.dist-info/LICENSE
yls-1.4.4.dist-info/LICENSE-THIRD-PARTY
yls-1.4.4.dist-info/METADATA
yls-1.4.4.dist-info/WHEEL
yls-1.4.4.dist-info/entry_points.txt
yls-1.4.4.dist-info/RECORD
