Metadata-Version: 2.3
Name: yls
Version: 1.4.4
Summary: YARA Language Server
License: MIT
Author: Matej Kašťák
Author-email: matej.kastak@avast.com
Maintainer: Matej Kašťák
Maintainer-email: matej.kastak@avast.com
Requires-Python: >=3.8,<4.0
Classifier: License :: OSI Approved :: MIT License
Classifier: Programming Language :: Python :: 3
Classifier: Programming Language :: Python :: 3.8
Classifier: Programming Language :: Python :: 3.9
Classifier: Programming Language :: Python :: 3.10
Classifier: Programming Language :: Python :: 3.11
Classifier: Programming Language :: Python :: 3.12
Classifier: Programming Language :: Python :: 3.13
Requires-Dist: pluggy (>=1.0.0,<2.0.0)
Requires-Dist: pygls (>=1.3.1,<2.0.0)
Requires-Dist: yaramod (>=4.3.0,<5.0.0)
Requires-Dist: yari-py (>=0.2.1,<0.3.0)
